CrystalStructure/__init__.py
CrystalStructure/atomic_site.py
CrystalStructure/base.py
CrystalStructure/crystal.py
CrystalStructure/examples.py
CrystalStructure/lattice.py
CrystalStructure/atomic_constants/__init__.py
CrystalStructure/atomic_constants/atomic_constants.py
CrystalStructure/atomic_constants/atomic_scattering_params.json
CrystalStructure/atomic_constants/covalent_radius.json
CrystalStructure/atomic_constants/vdw_radius.json
CrystalStructure/cifs/test1.cif
CrystalStructure/cifs/test2.cif
CrystalStructure-0.1.0.dist-info/METADATA
CrystalStructure-0.1.0.dist-info/WHEEL
CrystalStructure-0.1.0.dist-info/top_level.txt
CrystalStructure-0.1.0.dist-info/RECORD
