Metadata-Version: 2.1
Name: CrystalStructure
Version: 0.1.0
Summary: A python implementation of a Crystal Structure based on pymatgen
Author-email: Daniel Hollarek <daniel.hollarek@googlemail.com>
Project-URL: repository, https://github.com/aimat-lab/CrystalStructure
Requires-Dist: numpy <2.0.0
Requires-Dist: holytools
Requires-Dist: pymatgen
